simba/__init__.py
simba/functions.py
simba/model.py
simba/parameters.py
simba/util.py
simba/mat/__init__.py
simbapy-0.2.1.dist-info/METADATA
simbapy-0.2.1.dist-info/WHEEL
simbapy-0.2.1.dist-info/top_level.txt
simbapy-0.2.1.dist-info/RECORD
